{
    "variable": [
        {
            "id": "baseUrl",
            "key": "baseUrl",
            "type": "string",
            "name": "string",
            "value": "http:\/\/127.0.0.1:8000"
        }
    ],
    "info": {
        "name": "Laravel",
        "_postman_id": "5b56916d-4756-42a4-bf19-fc05dc7a86df",
        "description": "",
        "schema": "https:\/\/schema.getpostman.com\/json\/collection\/v2.1.0\/collection.json"
    },
    "item": [
        {
            "name": "Authentication",
            "description": "A collection of Authentication specific endpoints.",
            "item": [
                {
                    "name": "POST api\/v1\/login",
                    "request": {
                        "url": {
                            "host": "{{baseUrl}}",
                            "path": "api\/v1\/login",
                            "query": [],
                            "raw": "{{baseUrl}}\/api\/v1\/login"
                        },
                        "method": "POST",
                        "header": [
                            {
                                "key": "Content-Type",
                                "value": "application\/json"
                            },
                            {
                                "key": "Accept",
                                "value": "application\/json"
                            }
                        ],
                        "body": {
                            "mode": "raw",
                            "raw": "{\"email\":\"admin@admin.com\",\"password\":\"super-secret-password\"}"
                        },
                        "description": "",
                        "auth": {
                            "type": "noauth"
                        }
                    },
                    "response": []
                },
                {
                    "name": "POST api\/v1\/register",
                    "request": {
                        "url": {
                            "host": "{{baseUrl}}",
                            "path": "api\/v1\/register",
                            "query": [],
                            "raw": "{{baseUrl}}\/api\/v1\/register"
                        },
                        "method": "POST",
                        "header": [
                            {
                                "key": "Content-Type",
                                "value": "application\/json"
                            },
                            {
                                "key": "Accept",
                                "value": "application\/json"
                            }
                        ],
                        "body": {
                            "mode": "raw",
                            "raw": "{\"name\":\"\u7cfb\u7d71\u7ba1\u7406\u54e1\",\"email\":\"admin@admin.com\",\"password\":\"super-secret-password\"}"
                        },
                        "description": "",
                        "auth": {
                            "type": "noauth"
                        }
                    },
                    "response": []
                }
            ]
        }
    ],
    "auth": {
        "type": "noauth"
    }
}